arklog/__init__.py
arklog/colors.py
arklog/configuration.py
arklog/convenience.py
arklog/logger.py
arklog-0.7.0.dist-info/WHEEL
arklog-0.7.0.dist-info/METADATA
arklog-0.7.0.dist-info/RECORD
