Metadata-Version: 2.3
Name: arklog
Version: 0.7.0
Summary: Custom python logging formatter with color output.
Keywords: logging
Author: Arkadiusz Michał Ryś
Author-email: Arkadiusz Michał Ryś <Arkadiusz.Michal.Rys@gmail.com>
License: MIT License
Classifier: Development Status :: 2 - Pre-Alpha
Classifier: Intended Audience :: Developers
Classifier: License :: OSI Approved :: MIT License
Classifier: Natural Language :: English
Classifier: Programming Language :: Python :: 3
Requires-Dist: toml>=0.10.2
Requires-Dist: pyyaml>=6.0
Requires-Dist: ruff ; extra == 'dev'
Requires-Dist: invoke ; extra == 'dev'
Requires-Dist: vermin ; extra == 'dev'
Requires-Dist: sphinx ; extra == 'doc'
Requires-Dist: sphinx-rtd-theme ; extra == 'doc'
Requires-Dist: sphinx-tabs ; extra == 'doc'
Requires-Dist: sphinx-toolbox ; extra == 'doc'
Requires-Dist: sphinxext-opengraph ; extra == 'doc'
Requires-Dist: sphinx-notfound-page ; extra == 'doc'
Requires-Dist: sphinxcontrib-drawio ; extra == 'doc'
Requires-Dist: readthedocs-sphinx-search ; extra == 'doc'
Requires-Dist: myst-parser ; extra == 'doc'
Requires-Dist: pytest ; extra == 'test'
Requires-Python: >=3.12
Project-URL: source, https://git.rys.one/arrys/arklog
Provides-Extra: dev
Provides-Extra: doc
Provides-Extra: test
